LICENSE
README.md
pyproject.toml
setup.cfg
setup.py
src/data_science_libs.egg-info/PKG-INFO
src/data_science_libs.egg-info/SOURCES.txt
src/data_science_libs.egg-info/dependency_links.txt
src/data_science_libs.egg-info/not-zip-safe
src/data_science_libs.egg-info/requires.txt
src/data_science_libs.egg-info/top_level.txt
src/libs/__init__.py
src/libs/cross_validation_score.py
src/libs/mglearn.py
src/libs/pdummies_score.py
src/libs/simple_analyzer.py
src/libs/simple_hyper_tuner.py
src/libs/simple_processing.py
src/libs/simple_reducer.py
src/libs/simpleplotter.py
src/libs/single_scoring.py